{
	"description": "项目配置文件",
	"packOptions": {
		"ignore": []
	},
	"setting": {
		"urlCheck": false,
		"es6": true,
		"postcss": true,
		"preloadBackgroundData": false,
		"minified": true,
		"newFeature": true,
		"coverView": true,
		"autoAudits": false,
		"showShadowRootInWxmlPanel": true,
		"scopeDataCheck": false,
		"checkInvalidKey": true,
		"checkSiteMap": true,
		"uploadWithSourceMap": true,
		"babelSetting": {
			"ignore": [],
			"disablePlugins": [],
			"outputPath": ""
		},
		"useCompilerModule": true,
		"userConfirmedUseCompilerModuleSwitch": false
	},
	"compileType": "miniprogram",
	"libVersion": "2.12.0",
	"appid": "wxb2fd4e35d72d4ade",
	"projectname": "shijie",
	"debugOptions": {
		"hidedInDevtools": []
	},
	"isGameTourist": false,
	"simulatorType": "wechat",
	"simulatorPluginLibVersion": {},
	"condition": {
		"search": {
			"current": -1,
			"list": []
		},
		"conversation": {
			"current": -1,
			"list": []
		},
		"plugin": {
			"current": -1,
			"list": []
		},
		"game": {
			"currentL": -1,
			"list": []
		},
		"gamePlugin": {
			"current": -1,
			"list": []
		},
		"miniprogram": {
			"current": -1,
			"list": [
				{
					"id": -1,
					"name": "pages/personal/personal",
					"pathName": "pages/personal/personal",
					"query": "",
					"scene": null
				},
				{
					"id": -1,
					"name": "pages/category/category",
					"pathName": "pages/category/category",
					"query": "",
					"scene": null
				},
				{
					"id": -1,
					"name": "pages/details/details",
					"pathName": "pages/details/details",
					"query": "",
					"scene": null
				},
				{
					"id": -1,
					"name": "pages/search/search",
					"pathName": "pages/search/search",
					"query": "",
					"scene": null
				},
				{
					"id": -1,
					"name": "pages/search/result",
					"pathName": "pages/search/result",
					"query": "",
					"scene": null
				},
				{
					"id": -1,
					"name": "pages/category/category",
					"pathName": "pages/category/category",
					"query": "",
					"scene": null
				},
				{
					"id": -1,
					"name": "pages/shopping/shopping",
					"pathName": "pages/shopping/shopping",
					"query": "",
					"scene": null
				},
				{
					"id": -1,
					"name": "pages/contact/contact",
					"pathName": "pages/contact/contact",
					"query": "",
					"scene": null
				},
				{
					"id": -1,
					"name": "pages/set/feedback",
					"pathName": "pages/set/feedback",
					"query": "",
					"scene": null
				},
				{
					"id": -1,
					"name": "pages/set/modifyph",
					"pathName": "pages/set/modifyph",
					"query": "",
					"scene": null
				},
				{
					"id": -1,
					"name": "pages/data/data",
					"pathName": "pages/data/data",
					"query": "",
					"scene": null
				},
				{
					"id": -1,
					"name": "pages/set/modifyph",
					"pathName": "pages/set/modifyph",
					"query": "",
					"scene": null
				},
				{
					"id": -1,
					"name": "pages/set/modifypw",
					"pathName": "pages/set/modifypw",
					"query": "",
					"scene": null
				},
				{
					"id": -1,
					"name": "pages/order/order",
					"pathName": "pages/order/order",
					"query": "",
					"scene": null
				},
				{
					"id": -1,
					"name": "pages/login/login",
					"pathName": "pages/login/login",
					"query": "",
					"scene": null
				},
				{
					"id": -1,
					"name": "pages/pay/pay",
					"pathName": "pages/pay/pay",
					"query": "",
					"scene": null
				},
				{
					"id": -1,
					"name": "pages/myorder/myorder",
					"pathName": "pages/myorder/myorder",
					"query": "",
					"scene": null
				},
				{
					"id": -1,
					"name": "pages/evaluation/write",
					"pathName": "pages/evaluation/write",
					"query": "",
					"scene": null
				},
				{
					"id": -1,
					"name": "pages/bind/bind",
					"pathName": "pages/bind/bind",
					"query": "",
					"scene": null
				},
				{
					"id": -1,
					"name": "pages/authorization/authorization",
					"pathName": "pages/authorization/authorization",
					"query": "",
					"scene": null
				},
				{
					"id": -1,
					"name": "pages/wallet/wallet",
					"pathName": "pages/wallet/wallet",
					"query": "",
					"scene": null
				},
				{
					"id": -1,
					"name": "pages/address/address",
					"pathName": "pages/address/address",
					"query": "",
					"scene": null
				},
				{
					"id": -1,
					"name": "pages/address/modify",
					"pathName": "pages/address/modify",
					"query": "",
					"scene": null
				},
				{
					"id": -1,
					"name": "pages/collect/collect",
					"pathName": "pages/collect/collect",
					"query": "",
					"scene": null
				},
				{
					"id": -1,
					"name": "pages/myorder/refund",
					"pathName": "pages/myorder/refund",
					"query": "",
					"scene": null
				},
				{
					"id": -1,
					"name": "pages/myorder/refundList",
					"pathName": "pages/myorder/refundList",
					"query": "",
					"scene": null
				},
				{
					"id": -1,
					"name": "pages/integral/rule",
					"pathName": "pages/integral/rule",
					"query": "",
					"scene": null
				},
				{
					"id": -1,
					"name": "pages/integral/integral",
					"pathName": "pages/integral/integral",
					"query": "",
					"scene": null
				},
				{
					"id": -1,
					"name": "pages/topups/topups",
					"pathName": "pages/topups/topups",
					"query": "",
					"scene": null
				},
				{
					"id": -1,
					"name": "pages/popularize/popularize",
					"pathName": "pages/popularize/popularize",
					"query": "",
					"scene": null
				},
				{
					"id": -1,
					"name": "pages/tips/tips",
					"pathName": "pages/tips/tips",
					"query": "",
					"scene": null
				},
				{
					"id": -1,
					"name": "pages/topups/topups",
					"pathName": "pages/topups/topups",
					"query": "",
					"scene": null
				},
				{
					"id": -1,
					"name": "pages/info/info",
					"pathName": "pages/info/info",
					"query": "",
					"scene": null
				},
				{
					"id": -1,
					"name": "pages/search/result",
					"pathName": "pages/search/result",
					"query": "",
					"scene": null
				},
				{
					"id": -1,
					"name": "pages/topups/topups",
					"pathName": "pages/topups/topups",
					"query": "",
					"scene": null
				},
				{
					"id": -1,
					"name": "pages/wallet/wallet",
					"pathName": "pages/wallet/wallet",
					"query": "",
					"scene": null
				},
				{
					"id": -1,
					"name": "pages/popularize/popularize",
					"pathName": "pages/popularize/popularize",
					"query": "",
					"scene": null
				},
				{
					"id": -1,
					"name": "pages/topups/details",
					"pathName": "pages/topups/details",
					"query": "",
					"scene": null
				},
				{
					"id": -1,
					"name": "pages/myorder/refundList",
					"pathName": "pages/myorder/refundList",
					"query": "",
					"scene": null
				},
				{
					"id": -1,
					"name": "pages/topups/details",
					"pathName": "pages/topups/details",
					"scene": null
				}
			]
		}
	}
}